Metadata-Version: 2.1
Name: arcos
Version: 0.0.4
Summary: Economies of models
License: Apache 2.0
Author: Patrick Barker
Author-email: patrickbarkerco@gmail.com
Requires-Python: >=3.10.1,<3.11
Classifier: License :: Other/Proprietary License
Classifier: Programming Language :: Python :: 3
Requires-Dist: GitPython (>=3.1.26,<4.0.0)
Requires-Dist: blobz (==0.0.13)
Requires-Dist: cloudpickle (>=2.0.0,<3.0.0)
Requires-Dist: dacite (>=1.6.0,<2.0.0)
Requires-Dist: dataclasses-jsonschema (>=2.15.0,<3.0.0)
Requires-Dist: docker (>=5.0.3,<6.0.0)
Requires-Dist: docker-image-py (>=0.1.12,<0.2.0)
Requires-Dist: enlighten (>=1.10.2,<2.0.0)
Requires-Dist: genson (>=1.2.2,<2.0.0)
Requires-Dist: hurry.filesize (>=0.9,<0.10)
Requires-Dist: inflection (>=0.5.1,<0.6.0)
Requires-Dist: kubernetes (==24.2.0)
Requires-Dist: numpy (>=1.22.1,<2.0.0)
Requires-Dist: opencontainers[reggie] (>=0.0.12,<0.0.13)
Requires-Dist: pandas (>=1.3.5,<2.0.0)
Requires-Dist: schema (>=0.7.5,<0.8.0)
Requires-Dist: scikit-learn (>=1.0.2,<2.0.0)
Requires-Dist: simple-parsing (==0.0.20)
Requires-Dist: starlette (>=0.20.3,<0.21.0)
Requires-Dist: tableschema (>=1.20.2,<2.0.0)
Requires-Dist: tabulate (>=0.8.10,<0.9.0)
Requires-Dist: tomli (==1.2.3)
Requires-Dist: typeguard (>=2.13.3,<3.0.0)
Requires-Dist: types-PyYAML (>=6.0.11,<7.0.0)
Requires-Dist: types-six (>=1.16.19,<2.0.0)
Requires-Dist: types-tabulate (>=0.8.11,<0.9.0)
Requires-Dist: uvicorn[standard] (>=0.18.2,<0.19.0)
Requires-Dist: websocket-client (>=1.3.3,<2.0.0)
Requires-Dist: xdg (>=5.1.1,<6.0.0)
